lynxkite_mcp/__init__.py
lynxkite_mcp/mcp_server.py
lynxkite_mcp-0.2.0.dist-info/WHEEL
lynxkite_mcp-0.2.0.dist-info/entry_points.txt
lynxkite_mcp-0.2.0.dist-info/METADATA
lynxkite_mcp-0.2.0.dist-info/RECORD
