Metadata-Version: 2.3
Name: lynxkite-mcp
Version: 0.2.0
Summary: A command-line tool and MCP server for running LynxKite workspaces.
Classifier: License :: OSI Approved :: GNU Affero General Public License v3 or later (AGPLv3+)
Requires-Dist: lynxkite-core
Requires-Dist: mcp>=1.20.0
Requires-Python: >=3.11
Project-URL: Homepage, https://github.com/lynxkite/lynxkite-2000/
